{
  "$schema": "https://schema.management.azure.com/schemas/2015-01-01/deploymentParameters.json#",
  "contentVersion": "1.0.0.0",
  "parameters": {
    "dv_url": {
      "value": "https://mydataverseenvironment.crm11.dynamics.com/"
    },
    "dv_ClientID": {
      "value": "00000000-0000-0000-0000-000000000000"
    },
    "aad_objectID": {
      "value": "00000000-0000-0000-0000-000000000000"
    },
    "dv_ClientSecret": {
      "value": "mysecretvalue"
    },
    "onpremsql_connectionString": {
      "value": "integrated security=False;data source=localhost;initial catalog=D365CEADFDEMO_MSCRM;user id=adf-ir;password=mypassword;"
    }
  }
}